kservice/__init__.py
kservice/__main__.py
kservice/arguments.py
kservice/cmd_utils.py
kservice/colors.py
kservice/file_utils.py
kservice/k8s_utils.py
kservice/main.py
kservice/os_utils.py
minikservices-0.0.6.dist-info/LICENSE.txt
minikservices-0.0.6.dist-info/METADATA
minikservices-0.0.6.dist-info/WHEEL
minikservices-0.0.6.dist-info/entry_points.txt
minikservices-0.0.6.dist-info/top_level.txt
minikservices-0.0.6.dist-info/RECORD
